MANIFEST.in
README.md
glk.abi3.so
glk_build.py
requirements.txt
setup.py
setup.sh
scripts/tw-data
scripts/tw-make
scripts/tw-play
scripts/tw-stats
src/glk_comm.c
textworld/__init__.py
textworld/core.py
textworld/helpers.py
textworld/testing.py
textworld/text_utils.py
textworld/utils.py
textworld/agents/__init__.py
textworld/agents/human.py
textworld/agents/random.py
textworld/agents/simple.py
textworld/agents/walkthrough.py
textworld/challenges/__init__.py
textworld/challenges/coin_collector.py
textworld/challenges/treasure_hunter.py
textworld/challenges/utils.py
textworld/envs/__init__.py
textworld/envs/glulx/__init__.py
textworld/envs/glulx/git_glulx_ml.py
textworld/envs/wrappers/__init__.py
textworld/envs/wrappers/recorder.py
textworld/envs/wrappers/viewer.py
textworld/envs/zmachine/__init__.py
textworld/envs/zmachine/frotz.py
textworld/envs/zmachine/jericho.py
textworld/envs/zmachine/zork1.py
textworld/generator/__init__.py
textworld/generator/chaining.py
textworld/generator/dependency_tree.py
textworld/generator/game.py
textworld/generator/graph_networks.py
textworld/generator/logger.py
textworld/generator/maker.py
textworld/generator/testing.py
textworld/generator/text_generation.py
textworld/generator/text_grammar.py
textworld/generator/user_query.py
textworld/generator/vtypes.py
textworld/generator/world.py
textworld/generator/data/__init__.py
textworld/generator/data/logic/container.twl
textworld/generator/data/logic/door.twl
textworld/generator/data/logic/food.twl
textworld/generator/data/logic/inventory.twl
textworld/generator/data/logic/key.twl
textworld/generator/data/logic/object.twl
textworld/generator/data/logic/player.twl
textworld/generator/data/logic/room.twl
textworld/generator/data/logic/supporter.twl
textworld/generator/data/logic/thing.twl
textworld/generator/data/text_grammars/basic1_instruction.twg
textworld/generator/data/text_grammars/basic1_obj.twg
textworld/generator/data/text_grammars/basic1_room.twg
textworld_py.egg-info/PKG-INFO
textworld_py.egg-info/SOURCES.txt
textworld_py.egg-info/dependency_links.txt
textworld_py.egg-info/not-zip-safe
textworld_py.egg-info/requires.txt
textworld_py.egg-info/top_level.txt