Metadata-Version: 1.0
Name: textworld-py
Version: 0.0.3.4
Summary: Microsoft Textworld - A Text-based Learning Environment.
Home-page: UNKNOWN
Author: UNKNOWN
Author-email: UNKNOWN
License: UNKNOWN
Platform: UNKNOWN
